hlann/allotype.py
hlann/allotype_match.py
hlann/annotation.py
hlann/dataset.py
hlann/features.py
hlann/gene_features.py
hlann/gene_parser.py
hlann/genotype.py
hlann/genotype_match.py
hlann/haplotype.py
hlann/haplotype_match.py
hlann/hlann.py
hlann/hml_parser.py
hlann/individual.py
hlann/individual_match.py
hlann/match_list.py
hlann/matched_feat_enumeration.py
hlann/paired_matched_feat_enumeration.py
hlann/ref_data.py
hlann/ref_data_locus.py
hlann/res_pub_db.py
hlann/sequence.py
hlann/sequence_feat_searched.py
hlann/sequence_features.py
hlann/sequence_match.py
hlann/sequence_search.py
hlann/snp.py
hlann/util.py
hlann/data/agg-matcher-tool-publications-db.xlsx
hlann/data/alignments_A_gen_3240.csv.gz
hlann/data/alignments_A_gen_3370.csv.gz
hlann/data/alignments_A_gen_3380.csv.gz
hlann/data/alignments_A_gen_3390.csv.gz
hlann/data/alignments_A_gen_3410.csv.gz
hlann/data/alignments_A_gen_3430.csv.gz
hlann/data/alignments_A_gen_3440.csv.gz
hlann/data/alignments_A_gen_3460.csv.gz
hlann/data/alignments_A_gen_3470.csv.gz
hlann/data/alignments_A_gen_3480.csv.gz
hlann/data/alignments_A_gen_3490.csv.gz
hlann/data/alignments_A_gen_3500.csv.gz
hlann/data/alignments_A_gen_3510.csv.gz
hlann/data/alignments_A_prot_3240.csv.gz
hlann/data/alignments_A_prot_3370.csv.gz
hlann/data/alignments_A_prot_3380.csv.gz
hlann/data/alignments_A_prot_3390.csv.gz
hlann/data/alignments_A_prot_3410.csv.gz
hlann/data/alignments_A_prot_3430.csv.gz
hlann/data/alignments_A_prot_3440.csv.gz
hlann/data/alignments_A_prot_3460.csv.gz
hlann/data/alignments_A_prot_3470.csv.gz
hlann/data/alignments_A_prot_3480.csv.gz
hlann/data/alignments_A_prot_3490.csv.gz
hlann/data/alignments_A_prot_3500.csv.gz
hlann/data/alignments_A_prot_3510.csv.gz
hlann/data/alignments_B_gen_3240.csv.gz
hlann/data/alignments_B_gen_3370.csv.gz
hlann/data/alignments_B_gen_3380.csv.gz
hlann/data/alignments_B_gen_3390.csv.gz
hlann/data/alignments_B_gen_3410.csv.gz
hlann/data/alignments_B_gen_3430.csv.gz
hlann/data/alignments_B_gen_3440.csv.gz
hlann-0.0.5.dist-info/METADATA
hlann-0.0.5.dist-info/WHEEL
hlann-0.0.5.dist-info/top_level.txt
hlann-0.0.5.dist-info/RECORD
