Metadata-Version: 2.1
Name: hlann
Version: 0.0.5
Summary: HLA Annotation (HLAnn) Python package for annotating HLA
Author: NMDP Bioinformatics
Author-email: <rsajulga@nmdp.org>
License: LGPL 3.0
Keywords: hlann
Classifier: Development Status :: 3 - Alpha
Classifier: Intended Audience :: Science/Research
Classifier: Topic :: Scientific/Engineering :: Bio-Informatics
Classifier: License :: OSI Approved :: GNU Lesser General Public License v3 (LGPLv3)
Classifier: Natural Language :: English
Classifier: Programming Language :: Python :: 3.8
Classifier: Programming Language :: Python :: 3.9
Classifier: Programming Language :: Python :: 3.10
Classifier: Programming Language :: Python :: 2
Classifier: Programming Language :: Python :: 3
Classifier: Operating System :: MacOS :: MacOS X
Classifier: Operating System :: Microsoft :: Windows
Provides: hlann
Requires-Dist: allure-behave (==2.8.13)
Requires-Dist: api (>=0.0.7)
Requires-Dist: behave (==1.2.6)
Requires-Dist: biopython (==1.77)
Requires-Dist: click (<=8.0.4)
Requires-Dist: connexion[swagger-ui] (>=2.12.0)
Requires-Dist: editdistance (>=0.6.0)
Requires-Dist: Flask-Cors (==3.0.10)
Requires-Dist: inflect (==6.0.2)
Requires-Dist: openpyxl (==3.0.10)
Requires-Dist: pandas (==1.5.3)
Requires-Dist: protobuf (==3.20.0)
Requires-Dist: py-ard (==0.8.0)
Requires-Dist: py2neo (==2021.0.1)
Requires-Dist: PyHamcrest (==1.9.0)
Requires-Dist: regex (==2022.3.2)
Requires-Dist: SQLAlchemy (==1.4.41)
Requires-Dist: SQLAlchemy-Utils (==0.38.3)
